spac_kit/__init__.py
spac_kit/parser/Packets.py
spac_kit/parser/__init__.py
spac_kit/parser/downlink_to_excel.py
spac_kit/parser/logger.conf
spac_kit/parser/parse_ccsds_downlink.py
spac_kit/parser/remove_non_ccsds_headers.py
spac_kit/parser/test_utils.py
spac_kit/parser/util.py
spac_kit-0.1.0.dev0.dist-info/licenses/LICENSE.md
spac_kit-0.1.0.dev0.dist-info/METADATA
spac_kit-0.1.0.dev0.dist-info/WHEEL
spac_kit-0.1.0.dev0.dist-info/namespace_packages.txt
spac_kit-0.1.0.dev0.dist-info/top_level.txt
spac_kit-0.1.0.dev0.dist-info/zip-safe
spac_kit-0.1.0.dev0.dist-info/RECORD
