Metadata-Version: 2.4
Name: spac_kit
Version: 0.1.0.dev0
Summary: Collection of Python tools for working with CCSDS Space Packets
Home-page: https://github.com/CCSDSPy/SPaC-Kit
Author: NASA/Caltech/JPL
License: Apache License
Project-URL: Homepage, https://github.com/CCSDSPy/SPaC-Kit
Keywords: CCSDS,Space Packets,Downlink,Parser,Documentation
Classifier: Development Status :: 4 - Beta
Classifier: Environment :: Console
Classifier: Intended Audience :: Science/Research
Classifier: License :: OSI Approved :: Apache Software License
Classifier: Natural Language :: English
Classifier: Operating System :: OS Independent
Classifier: Programming Language :: Python :: 3 :: Only
Classifier: Topic :: Scientific/Engineering
Requires-Python: <3.10,>=3.9
License-File: LICENSE.md
Requires-Dist: ccsdspy~=1.3.0
Requires-Dist: crccheck~=1.3.0
Dynamic: license-file
